{
  "sections": {
    "page-top-banner": {
      "type": "page-top-banner",
      "disabled": true,
      "custom_css": [

      ],
      "settings": {
        "text": "We’re changing how<br>\nthe world drinks water."
      }
    },
    "versus": {
      "type": "richards-vs-competition",
      "disabled": true,
      "blocks": {
        "2a802754-fcb0-477a-9da4-72522935c0ba": {
          "type": "richards_product",
          "settings": {
            "title": "Richard’s® Still Rainwater",
            "product_image": "shopify:\/\/shop_images\/Richards-Still-product-Beauty.png",
            "product_information": "<p>Lorem ipsum dolor sit amet, consec tetuer adipiscing elit, sed diam nonummy nibh euismod tincidunt ut laoreet.<\/p>"
          }
        },
        "12c0558e-289d-4a74-8f54-9a6b43cb4abc": {
          "type": "richards_product",
          "settings": {
            "title": "Richard’s® Sparkling Rainwater",
            "product_image": "shopify:\/\/shop_images\/Richards-Sparkling-product-Beauty.png",
            "product_information": "<p>Lorem ipsum dolor sit amet, consec tetuer adipiscing elit, sed diam nonummy nibh euismod tincidunt ut laoreet. Ipsum lipsum.<\/p>"
          }
        },
        "47b1221f-a8e2-40d6-8471-df9bb54b31a7": {
          "type": "competitors_product",
          "settings": {
            "title": "Tap water",
            "product_image": "shopify:\/\/shop_images\/FPO-tap-water.jpg",
            "product_information": "<p>Lorem ipsum dolor sit amet, consec tetuer adipiscing nibh euismod tincidunt ut laoreet.<\/p>"
          }
        },
        "35a3c4bf-d6ab-414f-be54-36f4cc602a26": {
          "type": "competitors_product",
          "settings": {
            "title": "Artesian",
            "product_image": "shopify:\/\/shop_images\/FPO-bottle-artesian.jpg",
            "product_information": "<p>Lorem ipsum elit, sed diam nonummy nibh euismod tincidunt ut laoreet.<\/p>"
          }
        },
        "7bbd6c66-9f26-4d42-80a8-322246635b66": {
          "type": "competitors_product",
          "settings": {
            "title": "Mountain spring",
            "product_image": "shopify:\/\/shop_images\/FPO-bottle-water.jpg",
            "product_information": "<p>Lorem diam nonummy nibh euismod tincidunt ut laoreet.<\/p>"
          }
        }
      },
      "block_order": [
        "2a802754-fcb0-477a-9da4-72522935c0ba",
        "12c0558e-289d-4a74-8f54-9a6b43cb4abc",
        "47b1221f-a8e2-40d6-8471-df9bb54b31a7",
        "35a3c4bf-d6ab-414f-be54-36f4cc602a26",
        "7bbd6c66-9f26-4d42-80a8-322246635b66"
      ],
      "settings": {
        "heading": "How Richard’s Compares"
      }
    },
    "the-rainwater-model": {
      "type": "the-rainwater-model",
      "blocks": {
        "d7fdd667-e48a-4322-84d2-a80b18aefac3": {
          "type": "model_blocks",
          "settings": {
            "image": "shopify:\/\/shop_images\/rw-model-image-1.png",
            "heading": "Rains",
            "description": "<p>Our process begins at the same place all water starts – the <strong>rain.<\/strong> When clouds get filled to the brim, droplets fall from the sky.<\/p>"
          }
        },
        "e7eb975b-d346-4fbf-94cf-da6fc87fc2e7": {
          "type": "model_blocks",
          "settings": {
            "image": "shopify:\/\/shop_images\/rw-model-image-2_600290ef-37b8-4268-9eb6-d286622f2e12.png",
            "heading": "Rinse",
            "description": "<p>Rainfall is <strong>Mother Nature’s filtration system.<\/strong> During the first few minutes, raindrops <strong>clean the atmosphere<\/strong> and wash away any dirt or debris.<\/p>"
          }
        },
        "378937ef-79a4-4d1b-a7be-29994910244e": {
          "type": "model_blocks",
          "settings": {
            "image": "shopify:\/\/shop_images\/rw-model-image-3_bf362180-0cb6-4b46-a541-00f652ee3236.png",
            "heading": "Collect",
            "description": "<p>With our proprietary technology, we figure out the <strong>cleanest point<\/strong> in the rain cycle. Then we collect the <strong>pure raindrops<\/strong> into large vessels– think big honkin’ water towers of rain.<\/p>"
          }
        },
        "b281c460-36c7-4aae-a05d-7b81af897ab7": {
          "type": "model_blocks",
          "settings": {
            "image": "shopify:\/\/shop_images\/rw-model-image-4_c9824417-0e73-41cf-b137-f436900f22bd.png",
            "heading": "Filter",
            "description": "<p>Our closed loop filtration beats the highest drinking water standards and purifies with virtually <strong>zero water waste<\/strong>– 99% of the rainwater we collect ends up in your gullet. Compare that to reverse osmosis, which flushes 30-50% of collected water during filtration.<\/p>"
          }
        },
        "b8ef9699-9e69-4fad-93ed-e0a8a91de167": {
          "type": "model_blocks",
          "settings": {
            "image": "shopify:\/\/shop_images\/rw-model-image-5.png",
            "heading": "Bottle",
            "description": "<p>Clean-as-a-whistle <strong>rainwater<\/strong> goes into glass bottles and aluminum cans…packaging as <strong>infinitely renewable<\/strong> as the water itself.<\/p>"
          }
        },
        "bb5d5776-b14f-4309-837e-c1bbe6da19a3": {
          "type": "model_blocks",
          "settings": {
            "image": "shopify:\/\/shop_images\/rw-model-image-6.png",
            "heading": "Distribute",
            "description": "<p>Our fancy meteorological technology helps us place <strong>collection sites<\/strong> where the purest, most abundant rain falls so that we can be <strong>local everywhere.<\/strong><\/p>"
          }
        },
        "6f5800a2-ad8b-4418-80d4-b0d34afc3e22": {
          "type": "model_blocks",
          "settings": {
            "image": "shopify:\/\/shop_images\/rw-model-image-7.png",
            "heading": "Drink Up",
            "description": "<p>Before you know it, we’ve bottled <strong>the purest, best-tasting water<\/strong> from the one place it’ll never run out – <strong>the sky.<\/strong><\/p>"
          }
        }
      },
      "block_order": [
        "d7fdd667-e48a-4322-84d2-a80b18aefac3",
        "e7eb975b-d346-4fbf-94cf-da6fc87fc2e7",
        "378937ef-79a4-4d1b-a7be-29994910244e",
        "b281c460-36c7-4aae-a05d-7b81af897ab7",
        "b8ef9699-9e69-4fad-93ed-e0a8a91de167",
        "bb5d5776-b14f-4309-837e-c1bbe6da19a3",
        "6f5800a2-ad8b-4418-80d4-b0d34afc3e22"
      ],
      "settings": {
        "heading": "Getting Rain from Cloud to Bottle",
        "introduction": "<p>We are accessing the sky’s infinite water supply, we’re making sure we’re not wasting anything as we go.  While others lose almost half their water during filtration, our closed-loop system loses virtually zero. <\/p><h3>That’s right, zilch, zip, nada.<\/h3><p>That means we can use water more wisely, hydrate more people with each drop, and put more water into the drinking water supply. No other drinking water does that– not mountain springs, not mineral water, even tap.<\/p>"
      }
    },
    "pullquote": {
      "type": "pullquote",
      "disabled": true,
      "settings": {
        "quote_text": "Lorem ipsum dolor sit amet, consec tetuer adipiscing elit, sed diam nonummy nibh euismod tincidunt ut laoreet dolore magna aliquam erat volutpat."
      }
    },
    "8a2c0976-7156-47d0-b965-383ecc12c1cd": {
      "type": "callout-centered",
      "blocks": {
        "template--18984173764895__8a2c0976-7156-47d0-b965-383ecc12c1cd-1686681121792ee462-0": {
          "type": "heading",
          "settings": {
            "heading": "The cleanest water under the sun has the numbers to prove it.",
            "heading_size": "h2"
          }
        },
        "template--18984173764895__8a2c0976-7156-47d0-b965-383ecc12c1cd-1686681121792ee462-2": {
          "type": "button",
          "settings": {
            "button_label": "Download our water quality report",
            "button_link": "#"
          }
        }
      },
      "block_order": [
        "template--18984173764895__8a2c0976-7156-47d0-b965-383ecc12c1cd-1686681121792ee462-0",
        "template--18984173764895__8a2c0976-7156-47d0-b965-383ecc12c1cd-1686681121792ee462-2"
      ],
      "settings": {
      }
    },
    "b022380c-0067-42eb-8309-57fa6c889c18": {
      "type": "banner-grid-items",
      "blocks": {
        "e22aed70-6c1a-4772-a88e-5da23e0a3436": {
          "type": "icon_item",
          "settings": {
            "label": "Infinite Water Source",
            "text_color": "light_blue"
          }
        },
        "302ef9b9-ffac-4250-9858-b93e76131fcf": {
          "type": "icon_item",
          "settings": {
            "label": "Zero-Waste Filtration",
            "text_color": "pink"
          }
        },
        "11148169-9ea7-48a3-b29a-2aa6158a1561": {
          "type": "icon_item",
          "settings": {
            "label": "Renewable Packaging",
            "text_color": "red"
          }
        },
        "2fee22c9-1268-4ee5-9340-be9979d81d95": {
          "type": "icon_item",
          "settings": {
            "label": "More Water For More People",
            "text_color": "medium_blue"
          }
        }
      },
      "block_order": [
        "e22aed70-6c1a-4772-a88e-5da23e0a3436",
        "302ef9b9-ffac-4250-9858-b93e76131fcf",
        "11148169-9ea7-48a3-b29a-2aa6158a1561",
        "2fee22c9-1268-4ee5-9340-be9979d81d95"
      ],
      "settings": {
        "hero_image": "shopify:\/\/shop_images\/bg-home-banner-sky_df89ff10-7864-449e-8422-4cb4ffcbc9f9.jpg",
        "heading": "Making good on our good earth"
      }
    },
    "85f7042e-640c-4f3b-af6d-ecd56d2faa9e": {
      "type": "rainbow_text_banner",
      "disabled": true,
      "settings": {
        "text": "Annual Water Quality Report",
        "call_to_action_button_link": "#",
        "call_to_action_button_label": "Download annual report"
      }
    },
    "our-impact": {
      "type": "our-impact",
      "disabled": true,
      "blocks": {
        "e6794eba-2234-498b-9329-ff6a2a58e0af": {
          "type": "impact_item",
          "settings": {
            "image": "shopify:\/\/shop_images\/icon-saved.png",
            "image_custom_code": "",
            "title": "Saved",
            "content": "<p>Most importantly, our collection process saved over 400k gallons of water.  That’s enough water to hydrate 2000 people for an entire year!<\/p>"
          }
        },
        "5ad10781-badd-40c4-baf4-fefa253b681d": {
          "type": "impact_item",
          "settings": {
            "image": "shopify:\/\/shop_images\/icon-optimized.png",
            "image_custom_code": "",
            "title": "Optimized",
            "content": "<p>We optimized our packaging and are on track to save almost 50k pounds of cardboard in 2023.  That’s equal to saving 586 trees!<\/p>"
          }
        },
        "aa067ea9-dfc4-4c81-8857-cb6800a3df48": {
          "type": "impact_item",
          "settings": {
            "image": "shopify:\/\/shop_images\/icon-diverted.png",
            "image_custom_code": "",
            "title": "Diverted",
            "content": "<p>Diverted 7,725,224 plastic bottles from use, but we didn’t stop there!<\/p>"
          }
        }
      },
      "block_order": [
        "e6794eba-2234-498b-9329-ff6a2a58e0af",
        "5ad10781-badd-40c4-baf4-fefa253b681d",
        "aa067ea9-dfc4-4c81-8857-cb6800a3df48"
      ],
      "settings": {
        "heading": "Our impact",
        "call_to_action_button_link": "#",
        "call_to_action_button_label": "LEARN MORE ABOUT OUR IMPACT"
      }
    },
    "timeline-slider": {
      "type": "timeline-slider",
      "disabled": true,
      "blocks": {
        "cd30d0b7-51fc-4673-b4bd-90836e19f9ba": {
          "type": "timeline_slide",
          "settings": {
            "hero_image": "shopify:\/\/shop_images\/timeline-hero-1.jpg",
            "year": "1994",
            "title": "Richard catches his first drop",
            "content": "<p>Tired of well water that produced dirty dishes, dry hair, and cardboard-stiff jeans, Richard installed a rain collection system. He creates Tank Town to provide rainwater to his neighbors. <\/p>"
          }
        },
        "dd57e9a5-1532-4efd-bbc5-fb6b8ace02cf": {
          "type": "timeline_slide",
          "settings": {
            "hero_image": "shopify:\/\/shop_images\/timeline-hero-2.jpg",
            "year": "1998",
            "title": "Richard builds Tank Town",
            "content": "<p>Right outside of Austin, Texas, Tank Town is the birthplace of Richard’s Rainwater.<\/p>"
          }
        },
        "4e3ec816-d10d-4772-a646-b46122fc1609": {
          "type": "timeline_slide",
          "settings": {
            "hero_image": "shopify:\/\/shop_images\/timeline-hero-3.jpg",
            "year": "2002",
            "title": "Pioneering Bottled",
            "content": "<p>In 2002, Richard’s Rainwater becomes the first company in the nation to receive licensing to bottle and distribute rainwater.<\/p>"
          }
        },
        "19253d1c-d2e8-4ed1-bf1c-577ee4eed61b": {
          "type": "timeline_slide",
          "settings": {
            "hero_image": "shopify:\/\/shop_images\/timeline-hero-4.jpg",
            "year": "2008",
            "title": "Developing Sparkling Rainwater",
            "content": "<p>Since rainwater is free of minerals and additives, carbonation was a challenge. Richard developed his own recipe using time, ice-cold temps, and pressure.<\/p>"
          }
        },
        "904fbffc-be82-44ab-865b-5062e4745d07": {
          "type": "timeline_slide",
          "settings": {
            "hero_image": "shopify:\/\/shop_images\/timeline-hero-5.jpg",
            "year": "2019",
            "title": "Expanding with Lazy Magnolia",
            "content": "<p>Rainwater can be collected almost anywhere, making it the most sustainable water source. Richard’s partners with Lazy Magnolia Brewing in Mississippi to expand rain-catching operations.<\/p>"
          }
        },
        "d3bb3bef-6b9d-4d83-8895-ce69842a63c5": {
          "type": "timeline_slide",
          "settings": {
            "hero_image": "shopify:\/\/shop_images\/timeline-hero-6.jpg",
            "year": "2022",
            "title": "Growing with Faubourg",
            "content": "<p>Our newest partner, located in New Orleans, one of the top 3 Rainiest cities in the US. The World’s largest potable rainwater collection site.<\/p>"
          }
        }
      },
      "block_order": [
        "cd30d0b7-51fc-4673-b4bd-90836e19f9ba",
        "dd57e9a5-1532-4efd-bbc5-fb6b8ace02cf",
        "4e3ec816-d10d-4772-a646-b46122fc1609",
        "19253d1c-d2e8-4ed1-bf1c-577ee4eed61b",
        "904fbffc-be82-44ab-865b-5062e4745d07",
        "d3bb3bef-6b9d-4d83-8895-ce69842a63c5"
      ],
      "settings": {
        "heading": "Born in the Texas Sky"
      }
    },
    "42b4b5e7-aeba-47d4-a360-f05fa48d17e0": {
      "type": "stores-logo-slider",
      "settings": {
        "heading": "Find Richard’s near you.",
        "subheading": "If it rains where you live, there’s a good chance our rainwater is ‘round the corner.",
        "call_to_action_button_link": "shopify:\/\/pages\/store-locator",
        "call_to_action_button_label": "FIND YOUR NEAREST CLOUD"
      }
    },
    "main": {
      "type": "main-page",
      "disabled": true,
      "settings": {
        "padding_top": 28,
        "padding_bottom": 28
      }
    }
  },
  "order": [
    "page-top-banner",
    "versus",
    "the-rainwater-model",
    "pullquote",
    "8a2c0976-7156-47d0-b965-383ecc12c1cd",
    "b022380c-0067-42eb-8309-57fa6c889c18",
    "85f7042e-640c-4f3b-af6d-ecd56d2faa9e",
    "our-impact",
    "timeline-slider",
    "42b4b5e7-aeba-47d4-a360-f05fa48d17e0",
    "main"
  ]
}
